README.md
setup.py
imagehoster/__init__.py
imagehoster/upload.py
imagehoster.egg-info/PKG-INFO
imagehoster.egg-info/SOURCES.txt
imagehoster.egg-info/dependency_links.txt
imagehoster.egg-info/entry_points.txt
imagehoster.egg-info/requires.txt
imagehoster.egg-info/top_level.txt