Metadata-Version: 1.0
Name: imagehoster
Version: 0.0.1
Summary: Steemit Image Hoster Python Client
Home-page: http://github.com/emre/imagehoster-python-clilent
Author: emre yilmaz
Author-email: mail@emreyilmaz.me
License: MIT
Platform: UNKNOWN
